[
  {
    "id": "392f3c64",
    "name": "六5",
    "password": "003794",
    "createdAt": "2026-06-02T12:01:31.958Z",
    "updatedAt": "2026-06-02T12:01:37.628Z"
  },
  {
    "id": "b3f7dd30",
    "name": "六6",
    "password": "186559",
    "createdAt": "2026-06-02T12:01:47.337Z"
  },
  {
    "id": "2c2fab13",
    "name": "六7",
    "password": "765140",
    "createdAt": "2026-06-02T12:01:52.127Z"
  },
  {
    "id": "c37011bf",
    "name": "六8",
    "password": "815726",
    "createdAt": "2026-06-02T12:01:55.583Z"
  },
  {
    "id": "f438ed26",
    "name": "六9",
    "password": "978153",
    "createdAt": "2026-06-02T12:01:59.681Z"
  },
  {
    "id": "b4f9025a",
    "name": "六10",
    "password": "951585",
    "createdAt": "2026-06-02T12:03:03.372Z"
  },
  {
    "id": "db3ff2b2",
    "name": "示例",
    "password": "111111",
    "createdAt": "2026-06-02T12:01:14.508Z",
    "updatedAt": "2026-06-02T12:02:59.817Z"
  }
]